legacyhasher/__init__.py
legacyhasher/apps.py
legacyhasher/hashers.py
djlegacyhasher-1.0.0.dist-info/METADATA
djlegacyhasher-1.0.0.dist-info/WHEEL
djlegacyhasher-1.0.0.dist-info/licenses/AUTHORS.md
djlegacyhasher-1.0.0.dist-info/licenses/LICENSE
djlegacyhasher-1.0.0.dist-info/RECORD
