Metadata-Version: 2.4
Name: djlegacyhasher
Version: 1.0.0
Summary: Reading Django's old abandoned password hashers
Project-URL: homepage, https://gitlab.com/sanrep/djlegacyhasher
Project-URL: source, https://gitlab.com/sanrep/djlegacyhasher
Author-email: Sandi Šaban <saban.sandi@gmail.com>
License:                     GNU GENERAL PUBLIC LICENSE
License-File: AUTHORS.md
License-File: LICENSE
Classifier: Development Status :: 5 - Production/Stable
Classifier: Framework :: Django :: 5
Classifier: License :: OSI Approved :: GNU General Public License v3 (GPLv3)
Classifier: Natural Language :: English
Classifier: Programming Language :: Python :: 3
Requires-Python: >=3.13
Requires-Dist: django>=5
